cm_rgb/__init__.py
cm_rgb/ctrl.py
cm_rgb-0.2.1.data/scripts/cm-rgb-cli
cm_rgb-0.2.1.data/scripts/cm-rgb-monitor
cm_rgb-0.2.1.dist-info/LICENSE
cm_rgb-0.2.1.dist-info/METADATA
cm_rgb-0.2.1.dist-info/WHEEL
cm_rgb-0.2.1.dist-info/top_level.txt
cm_rgb-0.2.1.dist-info/RECORD
