Metadata-Version: 2.1
Name: cm-rgb
Version: 0.2.1
Summary: Utility to control RGB on AMD Wraith Prism
Home-page: http://github.com/cm-rgb
Author: gfduszynski
Author-email: gfduszynski@gmail.com
License: MIT
Keywords: rgb hid wraith
Platform: UNKNOWN
Classifier: Development Status :: 4 - Beta
Classifier: Topic :: Utilities
Classifier: License :: OSI Approved :: MIT License
Requires-Dist: hidapi
Requires-Dist: click
Requires-Dist: psutil
